{"site": null, "products": [{"name": "Tintas, vernizes e solu\u00e7\u00f5es de outros pol\u00edmeros sint\u00e9ticos, dispersos ou dissolvidos em meio n\u00e3o aquoso", "code": "32.0890"}, {"name": "Guarni\u00e7\u00f5es para m\u00f3veis, carro\u00e7arias ou semelhantes, de pl\u00e1sticos", "code": "39.2630"}, {"name": "Outras obras de pl\u00e1sticos e obras de outras mat\u00e9rias das posi\u00e7\u00f5es 39.01 a 39.04", "code": "39.2690"}, {"name": "Outras obras de madeira", "code": "44.2190"}, {"name": "Desperd\u00edcios e res\u00edduos de outras ligas de a\u00e7os", "code": "72.0429"}, {"name": "Produtos laminados planos, de ferro ou a\u00e7os n\u00e3o ligados, de largura => 600 mm, em rolos, laminados a frio, de espessura > 1 mm e < 3 mm, n\u00e3o folheados nem revestidos", "code": "72.0916"}, {"name": "Produtos laminados planos, de ferro ou a\u00e7os n\u00e3o ligados, de largura => 600 mm, n\u00e3o enrolados, laminados a frio, de espessura > 1 mm e < 3 mm, n\u00e3o folheados nem revestidos", "code": "72.0926"}, {"name": "Tubos e perfis ocos de outras ligas de a\u00e7os, sem costura, de se\u00e7\u00e3o circular, estirados ou laminados a frio", "code": "73.0451"}, {"name": "Tubos soldados, de se\u00e7\u00e3o circular, de ferro ou de a\u00e7o n\u00e3o ligados", "code": "73.0630"}, {"name": "Porcas de ferro fundido, ferro ou a\u00e7o", "code": "73.1816"}, {"name": "Outros artefatos roscados, de ferro fundido, ferro ou a\u00e7o", "code": "73.1819"}, {"name": "Arruelas de press\u00e3o e de seguran\u00e7a, n\u00e3o roscadas, de ferro fundido, ferro ou a\u00e7o", "code": "73.1821"}, {"name": "Outras arruelas de ferro fundido, ferro ou a\u00e7o", "code": "73.1822"}, {"name": "Outros artefatos n\u00e3o roscados, de ferro fundido, ferro ou a\u00e7o", "code": "73.1829"}, {"name": "Outras molas de ferro ou a\u00e7o", "code": "73.2090"}, {"name": "Outras obras moldadas, de ferro fundido, ferro ou a\u00e7o", "code": "73.2599"}, {"name": "Obras de fios de ferro ou a\u00e7o", "code": "73.2620"}, {"name": "Ferramentas intercambi\u00e1veis de embutir, estampar ou de puncionar, de metais comuns", "code": "82.0730"}, {"name": "Dobradi\u00e7as de qualquer tipo (inclu\u00eddos os gonzos e as charneiras), de metais comuns", "code": "83.0210"}, {"name": "Outras m\u00e1quinas e aparelhos mec\u00e2nicos com fun\u00e7\u00e3o pr\u00f3pria", "code": "84.7989"}, {"name": "Moldes para moldagem de borracha ou pl\u00e1sticos, por inje\u00e7\u00e3o ou compress\u00e3o", "code": "84.8071"}, {"name": "Mancais (chumaceiras) sem rolamentos; \"bronzes\"", "code": "84.8330"}, {"name": "Aparelhos de recep\u00e7\u00e3o, convers\u00e3o e transmiss\u00e3o ou regenera\u00e7\u00e3o de voz, imagens ou outros dados, incluindo os aparelhos de comuta\u00e7\u00e3o e roteamento", "code": "85.1762"}, {"name": "Outras partes e acess\u00f3rios de carro\u00e7arias (inclu\u00eddas as cabinas) para ve\u00edculos autom\u00f3veis das posi\u00e7\u00f5es 8701 a 8705", "code": "87.0829"}, {"name": "Outras partes e acess\u00f3rios, para ve\u00edculos autom\u00f3veis das posi\u00e7\u00f5es 8701 a 8705", "code": "87.0899"}, {"name": "Outros instrumentos, aparelhos e m\u00e1quinas de medida ou controle", "code": "90.3180"}, {"name": "Partes e acess\u00f3rios para instrumentos e aparelhos de medida ou controle", "code": "90.3190"}, {"name": "Assentos para ve\u00edculos autom\u00f3veis", "code": "94.0120"}, {"name": "Partes para m\u00f3veis", "code": "94.0390"}, {"name": "Partes de assentos", "code": "94.0190"}], "name": "Resil Minas Ind. e Com. Ltda.", "city": "S\u00e3o Joaquim de Bicas", "phones": [{"type": "telefone", "number": "55 (31) 3539-5214"}, {"type": "fax", "number": "55 (31) 3539-5303"}], "export_price_range": "De US$ 1 a 10 milh\u00f5es", "cep": "32920-000", "emails": ["elisangela@resilminas.com.br"], "state": "MG", "address": "Av. Jorge Sachs, 650", "contact_name": "Elisangela Maria Ara\u00fajo", "countries": ["\u00c1frica do Sul", "Argentina", "Egito", "Estados Unidos", "\u00cdndia", "It\u00e1lia", "Pol\u00f4nia", "Turquia", "Uruguai", "Venezuela"], "activity": "Fabrica\u00e7\u00e3o de pe\u00e7as e acess\u00f3rios para ve\u00edculos automotores n\u00e3o especificados anteriormente", "district": "Distrito Industrial  Prof. A. V."}