{"site": null, "products": [{"name": "Milho, exceto para semeadura", "code": "10.0590"}, {"name": "Outros a\u00e7\u00facares de cana, em bruto, sem adi\u00e7\u00e3o de aromatizantes ou de corantes", "code": "17.0114"}, {"name": "Outros a\u00e7\u00facares de cana, de beterraba e sacarose quimicamente pura, no estado s\u00f3lido", "code": "17.0199"}, {"name": "Outros sacos para embalagem, de outras mat\u00e9rias t\u00eaxteis", "code": "63.0590"}, {"name": "Soja, mesmo triturada", "code": "12.0100"}, {"name": "A\u00e7\u00facar de cana, em bruto, sem adi\u00e7\u00e3o de aromatizantes ou de corantes", "code": "17.0111"}, {"name": "\u00c1lcool et\u00edlico n\u00e3o desnaturado com volume de teor alco\u00f3lico => 80%", "code": "22.0710"}, {"name": "Tortas e outros res\u00edduos s\u00f3lidos da extra\u00e7\u00e3o do \u00f3leo de soja", "code": "23.0400"}], "name": "Usina Monte Alegre S.A. ", "city": "Monte Belo", "phones": [{"type": "telefone", "number": "55 (35) 3573-2500"}, {"type": "fax", "number": "55 (35) 3573-2500"}], "export_price_range": "De US$ 1 a 10 milh\u00f5es", "cep": "37115-000", "emails": ["umamg@umamg.com", "renato@umamg.com"], "state": "MG", "address": "Faz. Monte Alegre, s/n", "contact_name": "Renato Nogueira", "countries": ["\u00c1frica do Sul", "Alemanha", "Angola", "Ar\u00e1bia Saudita", "Arg\u00e9lia", "Bangladesh", "Cabo Verde, Republica De", "Camar\u00f5es", "Canad\u00e1", "China", "Cor\u00e9ia do Sul", "Egito", "El Salvador", "Emirados \u00c1rabes", "Espanha", "Estados Unidos", "Finl\u00e2ndia", "Formosa", "Fran\u00e7a", "Ge\u00f3rgia", "Guine", "Guine-Bissau", "Haiti", "Iemem", "\u00cdndia", "Indon\u00e9sia", "Ir\u00e3", "Israel", "Jamaica", "Jap\u00e3o", "Lib\u00e9ria", "Litu\u00e2nia", "Madagascar", "Mal\u00e1sia", "Marrocos", "Maur\u00edcio", "Mo\u00e7ambique", "Nig\u00e9ria", "Om\u00e3", "Pa\u00edses Baixos", "Paquist\u00e3o", "Peru", "Portugal", "Qu\u00eania", "Reino Unido", "Rep. Dominicana", "Rom\u00eania", "R\u00fassia", "Samoa", "Senegal", "S\u00edria", "Som\u00e1lia", "Sri Lanka", "Tanz\u00e2nia", "Togo", "Venezuela"], "activity": "Fabrica\u00e7\u00e3o de a\u00e7\u00facar em bruto", "district": "Sede"}