{"site": null, "products": [{"name": "Tintas e vernizes \u00e0 base de pol\u00edmeros acr\u00edlicos ou vin\u00edlicos dispersos ou dissolvidos em meio aquoso", "code": "32.0910"}, {"name": "Outros ve\u00edculos n\u00e3o autopropulsores", "code": "87.1680"}, {"name": "Tintas, vernizes e solu\u00e7\u00f5es \u00e0 base de poli\u00e9steres, dispersos ou dissolvidos em meio n\u00e3o aquoso", "code": "32.0810"}, {"name": "Tintas, vernizes e solu\u00e7\u00f5es de outros pol\u00edmeros sint\u00e9ticos, dispersos ou dissolvidos em meio n\u00e3o aquoso", "code": "32.0890"}], "name": "Olive Qu\u00edmica do Brasil Ltda.", "city": "S\u00e3o Caetano do Sul", "phones": [{"type": "telefone", "number": "55 (11) 4221-8484"}, {"type": "fax", "number": "55 (11) 4221-8484"}], "export_price_range": "At\u00e9 US$ 1 milh\u00e3o", "cep": "09520-070", "emails": ["everson@olive.com.br"], "state": "SP", "address": "Rua Amazonas, 363 4. Andar, Sl. 47", "contact_name": "Everson", "countries": ["Cuba", "Paraguai"], "activity": "Outros setores", "district": "Centro"}