{"site": null, "products": [{"name": "Outros fios texturizados de filamentos sint\u00e9ticos", "code": "54.0239"}, {"name": "Monofilamentos sint\u00e9ticos, t\u00edtulo => 67 decitex e se\u00e7\u00e3o transversal <= 1 mm", "code": "54.0410"}, {"name": "Outros monofilamentos de polipropileno, t\u00edtulo => 67 decitex e se\u00e7\u00e3o transversal <= 1 mm, com largura <= 5 mm", "code": "54.0412"}, {"name": "Monofilamentos artificiais, t\u00edtulo => 67 decitex e se\u00e7\u00e3o transversal <= 1 mm; l\u00e2minas e formas semelhantes de mat\u00e9rias t\u00eaxteis artificiais, com largura <= 5 mm", "code": "54.0500"}, {"name": "Fios de filamentos sint\u00e9ticos ou artificiais (exceto linhas para costurar), acondicionados para venda a retalho", "code": "54.0600"}, {"name": "Fios de filamentos artificiais, para venda a retalho", "code": "54.0620"}, {"name": "Tecidos de filamentos sint\u00e9ticos obtidos a partir de l\u00e2minas ou de formas semelhantes", "code": "54.0720"}, {"name": "Falsos tecidos de filamentos sint\u00e9ticos ou artificiais, de peso > 70 g/m\u00b2 e <= 150 g/m\u00b2", "code": "56.0313"}, {"name": "Outros sacos para embalagem, de l\u00e2minas ou formas semelhantes de polietileno ou polipropileno", "code": "63.0533"}, {"name": "Motores el\u00e9tricos de pot\u00eancia <= 37,5 W", "code": "85.0110"}, {"name": "Outros cord\u00e9is, cordas e cabos de polietileno ou polipropileno", "code": "56.0749"}], "name": "Nova Plast Ind. e Com. Ltda. ", "city": "Nova Odessa", "phones": [{"type": "telefone", "number": "55 (19) 3466-8700"}, {"type": "fax", "number": "55 (19) 3466-8719"}], "export_price_range": "Acima de US$ 50 milh\u00f5es", "cep": "01346-0-000", "emails": ["gustavo@novaplast.com.br", "carlos@novaplast.com.br"], "state": "SP", "address": "Av. Brasil, 800", "contact_name": "Carlos Cruz", "countries": ["Argentina", "Bol\u00edvia", "China", "Col\u00f4mbia", "Djibuti", "Espanha", "Iemem", "Pa\u00edses Baixos", "Panam\u00e1", "Paraguai"], "activity": "Abate de reses, exceto su\u00ednos", "district": "Distrito Industrial II"}