{"site": null, "products": [{"name": "Sab\u00f5es sob outras formas", "code": "34.0120"}, {"name": "Adesivos \u00e0 base de pol\u00edmeros das posi\u00e7\u00f5es 3901 a 3913 ou de borracha", "code": "35.0691"}, {"name": "Outras colas e adesivos preparados", "code": "35.0699"}, {"name": "Chapas, folhas, tiras, fitas, pel\u00edculas, de outros pl\u00e1sticos, sem suporte, n\u00e3o refor\u00e7adas", "code": "39.2099"}, {"name": "Outras formas e artigos, de borracha n\u00e3o vulcanizada", "code": "40.0690"}, {"name": "Papel auto-adesivo, em tiras ou em rolos", "code": "48.2311"}, {"name": "M\u00e1stique de vidraceiro, cimentos de resinas, outros m\u00e1stiques; indutos utilizados em pintura", "code": "32.1410"}, {"name": "Produtos utilizados como colas ou adesivos, acondicionados para venda a retalho, com peso l\u00edquido <= 1 kg", "code": "35.0610"}], "name": "Pulvitec S.A. Ind. e Com.", "city": "S\u00e3o Paulo", "phones": [{"type": "telefone", "number": "55 (11) 3869-2244"}, {"type": "fax", "number": "55 (11) 3869-4972"}], "export_price_range": "At\u00e9 US$ 1 milh\u00e3o", "cep": "05323-903", "emails": ["pulvitec@dglnet.com.br"], "state": "SP", "address": "Av. Pres. Altino, 2468", "contact_name": "Wanderley Hee", "countries": ["Alemanha", "Ar\u00e1bia Saudita", "Argentina", "Bol\u00edvia", "Chile", "El Salvador", "Equador", "Estados Unidos", "Gr\u00e9cia", "Honduras", "It\u00e1lia", "M\u00e9xico", "Paraguai", "Peru", "Uruguai"], "activity": "Fabrica\u00e7\u00e3o de adesivos e selantes", "district": "Jaguar\u00e9"}