{"site": null, "products": [{"name": "Sucos e extratos de outros vegetais (mam\u00e3o seco, semente de pomelo, ginkgo biloba seco)", "code": "13.0219"}, {"name": "Outros a\u00e7\u00facares no estado s\u00f3lido, xaropes de a\u00e7\u00facares, inclu\u00eddo o a\u00e7\u00facar invertido, suced\u00e2neos do mel, sem adi\u00e7\u00e3o de aromatizantes ou de corantes", "code": "17.0290"}, {"name": "Di\u00f3xido de sil\u00edcio", "code": "28.1122"}, {"name": "Outros oxicloretos e hidroxicloretos", "code": "28.2749"}, {"name": "Brometos de s\u00f3dio ou de pot\u00e1ssio", "code": "28.2751"}, {"name": "Metassilicatos de s\u00f3dio", "code": "28.3911"}, {"name": "Peroxoboratos (perboratos)", "code": "28.4030"}, {"name": "Outros \u00e1lcoois di\u00f3is, n\u00e3o saturados", "code": "29.0539"}, {"name": "Outros sais do \u00e1cido ac\u00e9tico", "code": "29.1529"}, {"name": "Outros \u00e1cidos monocarbox\u00edlicos ac\u00edclicos saturados, seus anidridos, per\u00f3xidos e per\u00e1cidos e seus derivados", "code": "29.1590"}, {"name": "Ortoftalatos de dioctila", "code": "29.1732"}, {"name": "\u00c9steres fosf\u00f3ricos, seus sais e derivados halogenados, sulfonados, nitrados ou nitrosados", "code": "29.1900"}, {"name": "Dietanolamina e seus sais", "code": "29.2212"}, {"name": "Outros amino\u00e1cidos, exceto que contenham mais de um tipo de fun\u00e7\u00e3o oxigenada, seus \u00e9steres e sais", "code": "29.2249"}, {"name": "Outros sais e hidr\u00f3xidos de am\u00f4nio quatern\u00e1rios", "code": "29.2390"}, {"name": "Isocianatos", "code": "29.2910"}, {"name": "Outros compostos de fun\u00e7\u00f5es nitrogenadas", "code": "29.2990"}, {"name": "Tiocarbamatos e ditiocarbamatos", "code": "29.3020"}, {"name": "Outros tiocompostos org\u00e2nicos", "code": "29.3090"}, {"name": "Outros compostos heteroc\u00edclicos exclusivamente de hetero\u00e1tomo(s) de nitrog\u00eanio", "code": "29.3399"}, {"name": "Corantes org\u00e2nico-sint\u00e9ticos dispersos e suas prepara\u00e7\u00f5es", "code": "32.0411"}, {"name": "Corantes b\u00e1sicos e suas prepara\u00e7\u00f5es", "code": "32.0413"}, {"name": "Pigmentos contendo, em peso, calculado sobre mat\u00e9ria seca, => 80% de di\u00f3xido de tit\u00e2nio", "code": "32.0611"}, {"name": "Tintas e vernizes \u00e0 base de pol\u00edmeros acr\u00edlicos ou vin\u00edlicos dispersos ou dissolvidos em meio aquoso", "code": "32.0910"}, {"name": "Folhas para marcar a ferro", "code": "32.1210"}, {"name": "Outros pigmentos dispersos em meios n\u00e3o aquosos, no estado l\u00edquido ou pastoso", "code": "32.1290"}, {"name": "Outras misturas de subst\u00e2ncias odor\u00edferas utilizadas como mat\u00e9ria b\u00e1sica para a ind\u00fastria", "code": "33.0290"}, {"name": "Agentes org\u00e2nicos de superf\u00edcie, ani\u00f4nicos, mesmo acondicionados para venda a retalho", "code": "34.0211"}, {"name": "Outros agentes org\u00e2nicos de superf\u00edcie, mesmo acondicionados para venda a retalho", "code": "34.0219"}, {"name": "Lix\u00edvias residuais da fabrica\u00e7\u00e3o de pasta de celulose, inclu\u00eddos os lignossulfonatos", "code": "38.0400"}, {"name": "Outros agentes de apresto ou acabamento para a ind\u00fastria do papel", "code": "38.0992"}, {"name": "Outros agentes de apresto ou acabamento para a ind\u00fastria do couro", "code": "38.0993"}, {"name": "Prepara\u00e7\u00f5es antioxidantes e outros estabilizadores compostos, para borracha ou pl\u00e1stico", "code": "38.1230"}, {"name": "Solventes e diluentes org\u00e2nicos compostos; prepara\u00e7\u00f5es para remover tintas ou vernizes", "code": "38.1400"}, {"name": "Outros produtos e prepara\u00e7\u00f5es das ind\u00fastrias qu\u00edmicas e conexas n\u00e3o inclu\u00eddos em outras posi\u00e7\u00f5es", "code": "38.2490"}, {"name": "Policloreto de vinila, n\u00e3o misturado com outras subst\u00e2ncias, forma prim\u00e1ria", "code": "39.0410"}, {"name": "Outros poli\u00e9steres, em formas prim\u00e1rias", "code": "39.0799"}, {"name": "Outras poliamidas, em formas prim\u00e1rias", "code": "39.0890"}, {"name": "Resinas melam\u00ednicas, em formas prim\u00e1rias", "code": "39.0920"}, {"name": "Outras resinas am\u00ednicas, em formas prim\u00e1rias", "code": "39.0930"}, {"name": "Poliuretanos, em formas prim\u00e1rias", "code": "39.0950"}, {"name": "Outros pap\u00e9is, cart\u00f5es, pasta de celulose e mantas de fibras de celulose, em rolos ou folhas", "code": "48.1190"}, {"name": "Esferas de vidro, n\u00e3o trabalhado", "code": "70.0210"}, {"name": "Chapas e tiras, de ligas alum\u00ednio, de espessura > 0,2 mm, de forma quadrada ou retangular", "code": "76.0612"}, {"name": "Outras ferramentas manuais, de metais comuns", "code": "82.0559"}, {"name": "Esp\u00e1tulas, abre-cartas, raspadeiras, apontadores de l\u00e1pis (apara-l\u00e1pis) e suas l\u00e2minas, de metais comuns", "code": "82.1410"}, {"name": "Derivados sulfonados dos hidrocarbonetos, seus sais e seus \u00e9steres et\u00edlicos", "code": "29.0410"}, {"name": "\u00c9steres do \u00e1cido acr\u00edlico", "code": "29.1612"}, {"name": "\u00c1cido ad\u00edpico, seus sais e \u00e9steres", "code": "29.1712"}, {"name": "Sais e \u00e9steres do \u00e1cido c\u00edtrico", "code": "29.1815"}, {"name": "Ur\u00e9ia, mesmo em solu\u00e7\u00e3o aquosa", "code": "31.0210"}, {"name": "Sulfato de am\u00f4nio", "code": "31.0221"}, {"name": "Corantes reagentes e suas prepara\u00e7\u00f5es", "code": "32.0416"}, {"name": "Prepara\u00e7\u00f5es \u00e0 base de mat\u00e9rias amil\u00e1ceas", "code": "38.0910"}, {"name": "Outros \u00e9teres de celulose, em formas prim\u00e1rias", "code": "39.1239"}, {"name": "Fios e cordas, de borracha, recobertos de t\u00eaxteis", "code": "56.0410"}, {"name": "Microesferas de vidro, de di\u00e2metro <= 1 mm", "code": "70.1820"}, {"name": "Glicose, no estado s\u00f3lido, e xarope de glicose, contendo, em peso, no estado seco, menos de 20% de frutose", "code": "17.0230"}, {"name": "Farinhas siliciosas f\u00f3sseis e outras terras siliciosas, de densidade aparente <= 1", "code": "25.1200"}, {"name": "Peroxossulfatos (persulfatos)", "code": "28.3340"}, {"name": "Outros compostos organo-inorg\u00e2nicos", "code": "29.3100"}, {"name": "Corantes \u00e0 cuba e suas prepara\u00e7\u00f5es", "code": "32.0415"}, {"name": "Pigmentos e suas prepara\u00e7\u00f5es", "code": "32.0417"}, {"name": "Outras mat\u00e9rias corantes org\u00e2nicas sint\u00e9ticas e suas prepara\u00e7\u00f5es", "code": "32.0419"}, {"name": "Produtos org\u00e2nicos sint\u00e9ticos utilizados como agentes de avivamento fluorescentes", "code": "32.0420"}, {"name": "Tintas de impress\u00e3o pretas", "code": "32.1511"}, {"name": "Outras tintas de impress\u00e3o", "code": "32.1519"}, {"name": "Sab\u00f5es sob outras formas", "code": "34.0120"}, {"name": "Agentes org\u00e2nicos de superf\u00edcie, n\u00e3o i\u00f4nicos, mesmo acondicionados para venda a retalho", "code": "34.0213"}, {"name": "Outras prepara\u00e7\u00f5es tensoativas e prepara\u00e7\u00f5es para lavagem e limpeza", "code": "34.0290"}, {"name": "Outras enzimas preparadas", "code": "35.0790"}, {"name": "Outros agentes de apresto ou acabamento, aceleradores de tingimento ou de fixa\u00e7\u00e3o e outros produtos para a ind\u00fastria t\u00eaxtil ou ind\u00fastrias similares", "code": "38.0991"}, {"name": "Outros pol\u00edmeros acr\u00edlicos, em formas prim\u00e1rias", "code": "39.0690"}, {"name": "Silicones, em formas prim\u00e1rias", "code": "39.1000"}], "name": "Texpal Qu\u00edmica Ltda.", "city": "Valinhos", "phones": [{"type": "telefone", "number": "55 (19) 3881-7999"}, {"type": "fax", "number": "55 (19) 3881-2511"}], "export_price_range": "At\u00e9 US$ 1 milh\u00e3o", "cep": "13279-404", "emails": ["vendas@texpal.com.br"], "state": "SP", "address": "Rua Texpal, 131, Cx. Postal 357", "contact_name": "Jos\u00e9 Antonio", "countries": ["Argentina", "Bol\u00edvia", "Chile", "Col\u00f4mbia", "Guatemala", "Honduras", "M\u00e9xico", "Paraguai", "Peru", "Portugal", "Rep. Dominicana", "Uruguai"], "activity": "Fabrica\u00e7\u00e3o de aditivos de uso industrial", "district": "Macuco"}