{"site": null, "products": [{"name": "Helic\u00f3pteros, de peso <= 2.000 kg, vazios", "code": "88.0211"}], "name": "Campneus L\u00edder de Pneum\u00e1ticos Ltda.", "city": "Campinas", "phones": [{"type": "telefone", "number": "55 (19) 3207-4355"}, {"type": "fax", "number": "55 (19) 3207-4355"}], "export_price_range": "At\u00e9 US$ 1 milh\u00e3o", "cep": "13091-611", "emails": ["mauricio.rodrigues@campneus.com.br"], "state": "SP", "address": "Av. Dr. Jos\u00e9 Bonif\u00e1cio C. Nogueira, 150, Salas 201/202", "contact_name": "Mauricio Rodrigues", "countries": ["Estados Unidos"], "activity": "Com\u00e9rcio de pe\u00e7as e acess\u00f3rios para ve\u00edculos automotores", "district": "Jd. Madalena"}