{"site": null, "products": [{"name": "Desperd\u00edcios, res\u00edduos e aparas, de outros pl\u00e1sticos", "code": "39.1590"}], "name": "Starpet Reciclagens Ltda.", "city": "Maracana\u00fa", "phones": [{"type": "telefone", "number": "55 (85) 3463-0774"}, {"type": "fax", "number": "55 (85) 3463-0774"}], "export_price_range": "De US$ 1 a 10 milh\u00f5es", "cep": "61901-410", "emails": ["starpet@terra.com.br"], "state": "CE", "address": "Via  de  Liga\u00e7\u00e3o 1, 1080", "contact_name": "Renata", "countries": ["China", "Estados Unidos", "Uruguai"], "activity": "Recupera\u00e7\u00e3o de materiais pl\u00e1sticos", "district": "Dist Indl. Iii"}