{"site": null, "products": [{"name": "Caf\u00e9 torrado, n\u00e3o descafeinado", "code": "09.0121"}, {"name": "Caf\u00e9 n\u00e3o torrado, n\u00e3o descafeinado", "code": "09.0111"}], "name": "Cambraia Com. Exp. e Imp. Ltda.", "city": "Nao cadstrado", "phones": [{"type": "telefone", "number": "55 (31) 3337-2226"}, {"type": "fax", "number": "55 (31) 3337-2226"}], "export_price_range": "At\u00e9 US$ 1 milh\u00e3o", "cep": "37262-000", "emails": ["henrique@cambraiacafes.com.br"], "state": "MG", "address": "Rua Jos\u00e9 Le\u00f4ncio Nascimento, 18, Cj. 102", "contact_name": "Henrique Cambraia", "countries": ["Alemanha", "China", "Estados Unidos", "It\u00e1lia", "Jap\u00e3o"], "activity": "Com\u00e9rcio atacadista de caf\u00e9 em gr\u00e3o", "district": "Barro Preto"}