{"site": null, "products": [{"name": "Tecidos de malha, com borracha", "code": "59.0691"}, {"name": "Cal\u00e7as, jardineiras, bermudas e \"shorts\", de malha, de algod\u00e3o, de uso feminino", "code": "61.0462"}, {"name": "Abrigos para esportes, de malha, de fibras sint\u00e9ticas", "code": "61.1212"}, {"name": "Blazers (casacos) de fibras sint\u00e9ticas, de uso feminino", "code": "62.0433"}, {"name": "Vestidos de fibras sint\u00e9ticas, de uso feminino", "code": "62.0443"}, {"name": "Saias e saias-cal\u00e7as, de fibras sint\u00e9ticas, de uso feminino", "code": "62.0453"}, {"name": "Cal\u00e7as, jardineiras, bermudas e \"shorts\", de fibras sint\u00e9ticas, de uso feminino", "code": "62.0463"}, {"name": "Cal\u00e7as, jardineiras, bermudas e \"shorts\", de outras mat\u00e9rias t\u00eaxteis, de uso feminino", "code": "62.0469"}, {"name": "Camisas, blusas, blusas \"chemisiers\", de algod\u00e3o, de uso feminino", "code": "62.0630"}, {"name": "Camisas, blusas, blusas \"chemisiers\", de fibras sint\u00e9ticas ou artificiais, de uso feminino", "code": "62.0640"}, {"name": "Shorts e sungas, de banho, exceto de malha, de uso masculino", "code": "62.1111"}, {"name": "Macac\u00f5es e conjuntos, de esqui, exceto de malha", "code": "62.1120"}, {"name": "Abrigos (fatos de treino) para esporte e outro vestu\u00e1rio n\u00e3o classificado em outra parte, de outras mat\u00e9rias t\u00eaxteis, de uso feminino", "code": "62.1149"}, {"name": "Mai\u00f4s e biqu\u00ednis, de banho, exceto de malha, de uso feminino", "code": "62.1112"}], "name": "S. Altman Biquini Brasil", "city": "S\u00e3o Paulo", "phones": [{"type": "telefone", "number": "55 (11) 3831-7769"}, {"type": "fax", "number": "55 (11) 3831-776955 () 3834-7774"}], "export_price_range": "At\u00e9 US$ 1 milh\u00e3o", "cep": "05075-020", "emails": ["saltman@biquinibrasil.com.br", "denise@biquinibrasil.com.br"], "state": "SP", "address": "Rua Gago Coutinho, 365", "contact_name": "Denise Altman", "countries": ["\u00c1frica do Sul", "Alemanha", "Austr\u00e1lia", "Canad\u00e1", "Can\u00e1rias, Ilhas", "Chipre", "Cingapura", "Cor\u00e9ia do Sul", "Espanha", "Estados Unidos", "Fran\u00e7a", "Gr\u00e9cia", "Honduras", "Hungria", "It\u00e1lia", "M\u00e9xico", "Panam\u00e1", "Pol\u00f4nia", "Porto Rico", "Portugal", "Reino Unido", "Uruguai", "Venezuela"], "activity": "Confec\u00e7\u00e3o de pe\u00e7as do vestu\u00e1rio, exceto roupas \u00edntimas", "district": "Lapa"}