{"site": null, "products": [{"name": "Impressos publicit\u00e1rios, cat\u00e1logos comerciais e semelhantes", "code": "49.1110"}, {"name": "Tubos soldados, de se\u00e7\u00e3o circular, de ferro ou de a\u00e7o n\u00e3o ligados", "code": "73.0630"}, {"name": "Torres e p\u00f3rticos, de ferro fundido, ferro ou a\u00e7o", "code": "73.0820"}, {"name": "Outras obras moldadas, de ferro fundido, ferro ou a\u00e7o", "code": "73.2599"}, {"name": "Outras obras de ferro ou a\u00e7o", "code": "73.2690"}, {"name": "Outras obras de alum\u00ednio", "code": "76.1699"}, {"name": "Partes de aparelhos de ilumina\u00e7\u00e3o, de vidro", "code": "94.0591"}, {"name": "Outros aparelhos el\u00e9tricos de ilumina\u00e7\u00e3o", "code": "94.0540"}, {"name": "Constru\u00e7\u00f5es e suas partes, de ferro fundido, ferro ou a\u00e7o", "code": "73.0890"}, {"name": "Lustres e outros aparelhos de ilumina\u00e7\u00e3o, el\u00e9tricos, pr\u00f3prios para serem suspensos ou fixados no teto ou na parede, exceto os utilizados na ilumina\u00e7\u00e3o p\u00fablica", "code": "94.0510"}], "name": "Clar\u00e3o Ind\u00fastria e Com\u00e9rcio de Iluminac\u00e3o Ltda", "city": "Nao cadstrado", "phones": [{"type": "telefone", "number": "55 (17) 3355-8800"}, {"type": "fax", "number": "131 (17) 3355-8800"}], "export_price_range": "At\u00e9 US$ 1 milh\u00e3o", "cep": "15061-480", "emails": ["vendas@clar\u00e3oiluminac\u00e3o.com.br", "alvaro.clar\u00e3o@clar\u00e3oiluminac\u00e3o.com.br"], "state": "SP", "address": "Av. Fernando Metittier, 1233", "contact_name": "Alvaro", "countries": ["Argentina", "Bol\u00edvia", "Costa Rica", "Paraguai", "Peru", "Uruguai"], "activity": "Fabrica\u00e7\u00e3o de l\u00e2mpadas e outros equipamentos de ilumina\u00e7\u00e3o", "district": "Jd Primavera"}