{"site": null, "products": [{"name": "Partes e acess\u00f3rios de m\u00e1quinas-ferramentas das posi\u00e7\u00f5es 8456 a 8461", "code": "84.6693"}, {"name": "Outras m\u00e1quinas e aparelhos mec\u00e2nicos com fun\u00e7\u00e3o pr\u00f3pria", "code": "84.7989"}, {"name": "M\u00e1quinas e aparelhos para misturar, amassar, moer, separar, peneirar, homogeneizar, emulsionar ou agitar", "code": "84.7982"}], "name": "Tintomatic Equipamentos Mecanicos Ltda", "city": "Salto", "phones": [{"type": "telefone", "number": "55 (19) 3500-4804"}, {"type": "fax", "number": "55 (19) 3500-4804"}], "export_price_range": "At\u00e9 US$ 1 milh\u00e3o", "cep": "13321-571", "emails": ["vendas@tintomatic.com.br", "claudio@tintomatic.com.br"], "state": "SP", "address": "Rua das Samambaias, 314", "contact_name": "Claudio", "countries": ["Alemanha", "Argentina", "Bol\u00edvia", "Col\u00f4mbia", "Cor\u00e9ia do Sul", "M\u00e9xico", "Paraguai"], "activity": "Fabrica\u00e7\u00e3o de m\u00e1quinas e equipamentos para uso industrial espec\u00edfico n\u00e3o especificados anteriormente", "district": "Centro"}