{"site": null, "products": [{"name": "Tortas e outros res\u00edduos s\u00f3lidos da extra\u00e7\u00e3o do \u00f3leo de soja", "code": "23.0400"}, {"name": "Outros agentes de apresto ou acabamento, aceleradores de tingimento ou de fixa\u00e7\u00e3o e outros produtos para a ind\u00fastria t\u00eaxtil ou ind\u00fastrias similares", "code": "38.0991"}, {"name": "Couros e peles curtidos, de bovinos ou de eq\u00fc\u00eddeos, depilados, no estado seco (\"crust\"), plena flor; n\u00e3o divididos; divididos, com a flor", "code": "41.0441"}, {"name": "Couro reconstitu\u00eddo \u00e0 base de couro ou de fibras de couro, em chapas, folhas ou tiras, mesmo enroladas", "code": "41.1100"}, {"name": "Ferro fundido bruto n\u00e3o ligado, contendo, em peso <= 0,5% de f\u00f3sforo", "code": "72.0110"}, {"name": "Couro reconstitu\u00eddo, \u00e0 base de couro ou de fibras de couro, em placas, folhas ou tiras, mesmo enroladas", "code": "41.1510"}, {"name": "Outras escovas que constituam partes de m\u00e1quinas, aparelhos ou de ve\u00edculos", "code": "96.0350"}], "name": "Recouro Ind. de Couro Reconstitu\u00eddo Ltda", "city": "Rio de Janeiro", "phones": [{"type": "telefone", "number": "55 (21) 2413-6133"}, {"type": "fax", "number": "55 (21) 2413-6155"}], "export_price_range": "De US$ 1 a 10 milh\u00f5es", "cep": "23065-480", "emails": ["recourorj@recouro.com.br", "helton@recouro.com.br"], "state": "RJ", "address": "Av. Brasil, 50340", "contact_name": "Helton Moretti", "countries": ["\u00c1frica do Sul", "Alemanha", "Argentina", "Bol\u00edvia", "Chile", "China", "Cingapura", "Col\u00f4mbia", "Cor\u00e9ia do Norte", "Cor\u00e9ia do Sul", "Egito", "El Salvador", "Equador", "Espanha", "Estados Unidos", "Formosa", "Fran\u00e7a", "Guatemala", "Hong Kong", "\u00cdndia", "It\u00e1lia", "L\u00edbano", "Mal\u00e1sia", "M\u00e9xico", "Pa\u00edses Baixos", "Paraguai", "Peru", "Portugal", "Tail\u00e2ndia", "Tun\u00edsia", "Turquia", "Uruguai", "Venezuela", "Virgens, Ilhas Brit\u00e2nicas"], "activity": "Curtimento e outras prepara\u00e7\u00f5es de couro", "district": "Campo Grande"}