{"site": null, "products": [{"name": "Manteiga", "code": "04.0510"}, {"name": "Queijos frescos (n\u00e3o curados), inclu\u00eddo o queijo do soro de leite e o requeij\u00e3o", "code": "04.0610"}, {"name": "Tortas e outros res\u00edduos s\u00f3lidos da extra\u00e7\u00e3o do \u00f3leo de soja", "code": "23.0400"}], "name": "Eleg\u00ea Alimentos S.A.", "city": "Porto Alegre", "phones": [{"type": "telefone", "number": "55 (51) 3371-3337"}, {"type": "fax", "number": "55 (51) 3371-2831"}], "export_price_range": "De US$ 1 a 10 milh\u00f5es", "cep": "90200-290", "emails": ["comex@avipal.com.br"], "state": "RS", "address": "Av. das Ind\u00fastrias, 720", "contact_name": "Gilvan Bach", "countries": ["Arg\u00e9lia", "Bulg\u00e1ria", "Egito", "Fran\u00e7a", "Guine", "Kwait", "L\u00edbano", "R\u00fassia"], "activity": "Prepara\u00e7\u00e3o do leite", "district": "Anchieta"}